HaiGF/__init__.py
HaiGF/__main__.py
HaiGF/version.py
HaiGF/apis/__init__.py
HaiGF/apis/apis.py
HaiGF/apis/hai_client.py
HaiGF/gui_framework/__init__.py
HaiGF/gui_framework/config/HGF.py
HaiGF/gui_framework/config/__init__.py
HaiGF/gui_framework/config/default_config.yaml
HaiGF/gui_framework/config/enum.py
HaiGF/gui_framework/config/icons.py
HaiGF/gui_framework/config/preset.py
HaiGF/gui_framework/main_window/__init__.py
HaiGF/gui_framework/main_window/main_window.py
HaiGF/gui_framework/main_window/ui_form.py
HaiGF/gui_framework/main_window/actions/__init__.py
HaiGF/gui_framework/main_window/actions/actions.py
HaiGF/gui_framework/utils/__init__.py
HaiGF/gui_framework/utils/_io.py
HaiGF/gui_framework/utils/image.py
HaiGF/gui_framework/utils/plugin_manager.py
HaiGF/gui_framework/utils/qt.py
HaiGF/gui_framework/utils/shape.py
HaiGF/gui_framework/widgets/__init__.py
HaiGF/gui_framework/widgets/aux_side_bar/__init__.py
HaiGF/gui_framework/widgets/aux_side_bar/aux_side_bar.py
HaiGF/gui_framework/widgets/common/__init__.py
HaiGF/gui_framework/widgets/common/blue_button.py
HaiGF/gui_framework/widgets/common/hai_action.py
HaiGF/gui_framework/widgets/common/hai_msb_widget.py
HaiGF/gui_framework/widgets/common/hai_page.py
HaiGF/gui_framework/widgets/common/hai_plugin.py
HaiGF/gui_framework/widgets/common/hai_splitter.py
HaiGF/gui_framework/widgets/common/item_model.py
HaiGF/gui_framework/widgets/common/title_bar_with_action.py
HaiGF/gui_framework/widgets/main_side_bar/__init__.py
HaiGF/gui_framework/widgets/main_side_bar/explorer_widget.py
HaiGF/gui_framework/widgets/main_side_bar/main_side_bar.py
HaiGF/gui_framework/widgets/menu_bar/__init__.py
HaiGF/gui_framework/widgets/menu_bar/hai_menu_bar.py
HaiGF/gui_framework/widgets/panel/__init__.py
HaiGF/gui_framework/widgets/panel/panel_widget.py
HaiGF/gui_framework/widgets/status_bar/__init__.py
HaiGF/gui_framework/widgets/status_bar/hai_status_bar.py
HaiGF/plugins/__init__.py
HaiGF/plugins/annotation_tools/__init__.py
hai_gui_framework-0.0.6.dist-info/METADATA
hai_gui_framework-0.0.6.dist-info/WHEEL
hai_gui_framework-0.0.6.dist-info/top_level.txt
hai_gui_framework-0.0.6.dist-info/RECORD
