Metadata-Version: 2.1
Name: hai-gui-framework
Version: 0.0.6
Summary: HaiGF is the Hakutaku Artificial Intelligence (HAI) GUI Framework, which provides a set of APIs for building GUI applications in HAI Platform.
Home-page: https://github.com/zhangzhengde0225/hai-gui-framework
Author: Zhengde Zhang
Author-email: drivener@163.com
License: MIT
Classifier: License :: OSI Approved :: MIT License
Classifier: Programming Language :: Python
Classifier: Programming Language :: Python :: 3
Classifier: Programming Language :: Python :: 3.6
Classifier: Programming Language :: Python :: 3.7
Classifier: Programming Language :: Python :: 3.8
Classifier: Programming Language :: Python :: 3.9
Classifier: Programming Language :: Python :: Implementation :: CPython
Classifier: Programming Language :: Python :: Implementation :: PyPy
Requires-Python: >=3.6.0
Requires-Dist: pyside2
Requires-Dist: numpy
Requires-Dist: pillow
Requires-Dist: opencv-python
Requires-Dist: easydict
Requires-Dist: pyyaml
Requires-Dist: damei
Requires-Dist: pyqtgraph
Requires-Dist: grpcio-tools
